README.md
setup.py
lomp/__init__.py
lomp/lomp.py
lomp.egg-info/PKG-INFO
lomp.egg-info/SOURCES.txt
lomp.egg-info/dependency_links.txt
lomp.egg-info/top_level.txt