Metadata-Version: 1.1
Name: lomp
Version: 0.0.6
Summary: Memory-efficient parallelism
Home-page: https://github.com/jimrybarski/lowmem-parallel
Author: Jim Rybarski
Author-email: jim@rybarski.com
License: UNKNOWN
Download-URL: https://github.com/jimrybarski/lowmem-parallel/tarball/0.0.6
Keywords: memory,parallel,parallelism
Platform: UNKNOWN
Classifier: Development Status :: 3 - Alpha
Classifier: License :: Freely Distributable
Classifier: License :: OSI Approved :: BSD License
Classifier: Operating System :: POSIX :: Linux
Classifier: Programming Language :: Python :: 2.7
Classifier: Programming Language :: Python :: 3.3
Classifier: Programming Language :: Python :: 3.4
Classifier: Programming Language :: Python :: 3.5
Classifier: Programming Language :: Python :: 3.6
Classifier: Programming Language :: Python :: 3.7
